README.rst
setup.cfg
setup.py
jenkins_job_builder_active_choice.egg-info/PKG-INFO
jenkins_job_builder_active_choice.egg-info/SOURCES.txt
jenkins_job_builder_active_choice.egg-info/dependency_links.txt
jenkins_job_builder_active_choice.egg-info/entry_points.txt
jenkins_job_builder_active_choice.egg-info/top_level.txt
jenkins_jobs_active_choice/__init__.py
jenkins_jobs_active_choice/active_choice.py