Metadata-Version: 1.1
Name: jenkins-job-builder-active-choice
Version: 0.0.5
Summary: Jenkins Job Builder Active Choice Parameter builder
Home-page: https://github.com/bgaifullin/jenkins-job-builder-active-choice
Author: Bulat Gaifullin
Author-email: gaifullinbf@gmail.com
License: MIT license
Platform: UNKNOWN
Classifier: Environment :: Console
Classifier: Intended Audience :: Developers
Classifier: Intended Audience :: Information Technology
Classifier: License :: OSI Approved :: Apache Software License
Classifier: Operating System :: OS Independent
Classifier: Programming Language :: Python
Classifier: Programming Language :: Python :: 2
Classifier: Programming Language :: Python :: 3
